episcen/__init__.py
episcen/mixing.py
episcen/model.py
episcen/version.py
episcen-0.1.0.dist-info/LICENSE
episcen-0.1.0.dist-info/METADATA
episcen-0.1.0.dist-info/WHEEL
episcen-0.1.0.dist-info/top_level.txt
episcen-0.1.0.dist-info/zip-safe
episcen-0.1.0.dist-info/RECORD
